Workbook

Sheet Hypothèses
A1: CUSTOMER & GROWTH AI LAB - HYPOTHÈSES DES BUSINESS CASES
A2: Modifiez les cellules en fond vert léger ci-dessous pour recalculer dynamiquement les modèles.
A4: Code Hypothèse | B4: Description de l'Hypothèse | C4: Valeur | D4: Unité | E4: Source / Validation
A5: COST_CONTACT | B5: Coût unitaire de contact CRM (Phoning / SMS) | C5: 2 | D5: £ / client | E5: Estimation CRM direct
A6: RESP_RATE | B6: Taux de conversion / réengagement estimé | C6: 0.06 | D6: % | E6: Historique campagnes CRM
A7: MARGIN_RATE | B7: Taux de marge brute moyen sur les ventes | C7: 0.4 | D7: % | E7: Comptabilité analytique
A8: SKU_COST | B8: Coût de complexité logistique annuel par SKU | C8: 500 | D8: £ / SKU / an | E8: Analyse coûts fixes Supply
A9: TRANSFER_RATE | B9: Taux de transfert d'achat vers SKUs A/B | C9: 0.5 | D9: % | E9: Merchandising / Substituts
A10: CONTROL_PCT | B10: Part des clients réservés au groupe de contrôle | C10: 0.1 | D10: % | E10: Méthodologie AB Testing

Sheet Business Case A (Reconquête)
A1: BUSINESS CASE A : RECONQUÊTE DES CLIENTS À RISQUE
A2: Recalcul dynamique lié aux cellules de l'onglet 'Hypothèses'.
A4: Indicateur Financier / Opérationnel | B4: Formule Excel / Valeur | C4: Unité
A5: Volume de clients ciblés (À risque) | B5: 828 | C5: clients
A6: Part du groupe de contrôle | B6: ='Hypothèses'!C10 | C6: %
A7: Volume du groupe de contrôle | B7: =ROUND(B5*B6, 0) | C7: clients (AB Testing)
A8: Volume réellement contacté (Traitement) | B8: =B5-B7 | C8: clients
A9: Coût unitaire de contact | B9: ='Hypothèses'!C5 | C9: £ / client
A10: Investissement Total (Coût Campagne) | B10: =B8*B9 | C10: £
A11: Panier Moyen Historique du Segment | B11: 1978.4164 | C11: £
A12: Taux de Réponse (Conversion) | B12: ='Hypothèses'!C6 | C12: %
A13: Nombre de clients réengagés | B13: =B8*B12 | C13: clients
A14: Chiffre d'Affaires Brut Généré | B14: =B13*B11 | C14: £
A15: Taux de Marge Brute | B15: ='Hypothèses'!C7 | C15: %
A16: Marge Brute Générée | B16: =B14*B15 | C16: £
A17: GAIN NET FINANCIER (Marge - Coût) | B17: =B16-B10 | C17: £
A18: Seuil de Rentabilité (Break-even Rate) | B18: =B9/(B11*B15) | C18: % réengagement minimum
A19: RETOUR SUR INVESTISSEMENT (ROI) | B19: =B17/B10 | C19: % ROI Net

Sheet Business Case B (SKUs)
A1: BUSINESS CASE B : RATIONALISATION DU CATALOGUE SKUS
A2: Recalcul dynamique lié aux cellules de l'onglet 'Hypothèses'.
A4: Indicateur Financier / Logistique | B4: Formule Excel / Valeur | C4: Unité
A5: Volume de SKUs C déréférencés | B5: 176 | C5: références C
A6: Chiffre d'Affaires Historique des SKUs | B6: 14020.87 | C6: £
A7: Taux de transfert d'achat vers SKUs A/B | B7: ='Hypothèses'!C9 | C7: %
A8: Part de CA perdu définitivement | B8: =1-B7 | C8: %
A9: Chiffre d'Affaires Perdu | B9: =B6*B8 | C9: £
A10: Taux de Marge Brute | B10: ='Hypothèses'!C7 | C10: %
A11: Marge Brute Perdue | B11: =B9*B10 | C11: £ (Coût d'opportunité)
A12: Coût annuel de complexité par SKU | B12: ='Hypothèses'!C8 | C12: £ / SKU / an
A13: Économies Logistiques Annuelles | B13: =B5*B12 | C13: £ de coûts fixes économisés
A14: GAIN NET FINANCIER ANNUEL | B14: =B13-B11 | C14: £ Gain Net
